Practice/MUX/MUX.v
module MUX (A, B, SEL, OUT);

input A, B, SEL;
output OUT;

assign OUT = (A|B|SEL)&(A|B|~SEL)&(A|~B|SEL)&(~A|B|~SEL);

endmodule

Practice/MUX/MUX_tb.v
`timescale 1ps/1ps
`include "MUX.v"

module MUX_tb;

    reg A, B, SEL;
    wire OUT;

    MUX uut (.A(A), .B(B), .SEL(SEL), .OUT(OUT));

    initial begin

        $dumpfile("wave.vcd");
        $dumpvars(0, MUX_tb);

        A = 0; B = 0; SEL = 0;
        #10
        A = 0; B = 0; SEL = 1;
        #10
        A = 0; B = 1; SEL = 0;
        #10
        A = 0; B = 1; SEL = 1;
        #10
        A = 1; B = 0; SEL = 0;
        #10
        A = 1; B = 0; SEL = 1;
        #10
        A = 1; B = 1; SEL = 0;
        #10
        A = 1; B = 1; SEL = 1;
        #10

        $finish;


    
    end

endmodule

Practice/MUX/wave.vcd
$date
	Tue Jun  3 18:20:21 2025
$end
$version
	Icarus Verilog
$end
$timescale
	1ps
$end
$scope module MUX_tb $end
$var wire 1 ! OUT $end
$var reg 1 " A $end
$var reg 1 # B $end
$var reg 1 $ SEL $end
$scope module uut $end
$var wire 1 " A $end
$var wire 1 # B $end
$var wire 1 ! OUT $end
$var wire 1 $ SEL $end
$upscope $end
$upscope $end
$enddefinitions $end
$comment Show the parameter values. $end
$dumpall
$end
#0
$dumpvars
0$
0#
0"
0!
$end
#10
1$
#20
0$
1#
#30
1!
1$
#40
0$
0#
1"
#50
0!
1$
#60
1!
0$
1#
#70
1$
